nua/orchestrator/__init__.py
nua/orchestrator/__main__.py
nua/orchestrator/admin_local.py
nua/orchestrator/api.py
nua/orchestrator/app_deployer.py
nua/orchestrator/app_instance.py
nua/orchestrator/app_manager.py
nua/orchestrator/assign/__init__.py
nua/orchestrator/assign/engine.py
nua/orchestrator/assign/evaluators.py
nua/orchestrator/assign/gen_db_credentials.py
nua/orchestrator/backup/__init__.py
nua/orchestrator/backup/app_backup.py
nua/orchestrator/backup/app_restore.py
nua/orchestrator/backup/backup_component.py
nua/orchestrator/backup/backup_record.py
nua/orchestrator/backup/backup_registry.py
nua/orchestrator/backup/backup_report.py
nua/orchestrator/backup/plugins/__init__.py
nua/orchestrator/backup/plugins/mongodump.py
nua/orchestrator/backup/plugins/mysqldump.py
nua/orchestrator/backup/plugins/pg_dump.py
nua/orchestrator/backup/plugins/plugin_base_class.py
nua/orchestrator/backup/plugins/tgz_volumes.py
nua/orchestrator/backup/provider_backup.py
nua/orchestrator/backup/volume_backup.py
nua/orchestrator/bootstrap/__init__.py
nua/orchestrator/bootstrap/bootstrap.py
nua/orchestrator/certbot/__init__.py
nua/orchestrator/certbot/certbot.py
nua/orchestrator/certbot/commands.py
nua/orchestrator/certbot/config/__init__.py
nua/orchestrator/certbot/config/cli.ini
nua/orchestrator/certbot/config/options-ssl-nginx.conf
nua/orchestrator/certbot/installer.py
nua/orchestrator/cli/__init__.py
nua/orchestrator/cli/commands/__init__.py
nua/orchestrator/cli/commands/backup_restore.py
nua/orchestrator/cli/commands/deploy_remove.py
nua/orchestrator/cli/commands/restore_deployed.py
nua/orchestrator/cli/commands/start_stop.py
nua/orchestrator/cli/commands/status.py
nua/orchestrator/cli/configuration.py
nua/orchestrator/cli/debug.py
nua/orchestrator/cli/main.py
nua/orchestrator/config.py
nua/orchestrator/constants.py
nua/orchestrator/db/__init__.py
nua/orchestrator/db/create.py
nua/orchestrator/db/model/__init__.py
nua/orchestrator/db/model/auth.py
nua_orchestrator-0.5.43.dist-info/METADATA
nua_orchestrator-0.5.43.dist-info/WHEEL
nua_orchestrator-0.5.43.dist-info/entry_points.txt
nua_orchestrator-0.5.43.dist-info/RECORD
