Metadata-Version: 2.1
Name: nua-orchestrator
Version: 0.5.43
Summary: Nua orchestrator - local implementation
Home-page: https://github.com/abilian/nua
License: Apache-2.0
Author: Stefane Fermigier
Author-email: sf@abilian.com
Requires-Python: >=3.10,<4.0
Classifier: Development Status :: 3 - Alpha
Classifier: Environment :: Console
Classifier: Intended Audience :: Developers
Classifier: Intended Audience :: System Administrators
Classifier: License :: OSI Approved :: Apache Software License
Classifier: Programming Language :: Python :: 3
Classifier: Programming Language :: Python :: 3.10
Classifier: Programming Language :: Python :: 3.11
Requires-Dist: SQLAlchemy (>=1.4.36,<2.0.0)
Requires-Dist: SQLAlchemy-serializer (>=1.4.1,<2.0.0)
Requires-Dist: docker (>=6,<7)
Requires-Dist: nua-lib (==0.5.43)
Requires-Dist: paramiko (>=2.11.0,<3.0.0)
Requires-Dist: psycopg2-binary (>=2.9.3,<3.0.0)
Requires-Dist: python-dotenv (>=0.21,<0.22)
Requires-Dist: pyyaml (>=6,<7)
Requires-Dist: setuptools
Requires-Dist: tomli (>=2,<3)
Requires-Dist: typer[all] (>=0.7.0,<0.8.0)
Requires-Dist: wheel
Project-URL: Documentation, https://nua.rocks/
Project-URL: Repository, https://github.com/abilian/nua
